{
  "ADAI": "ADANAC INVESTMENT CO LTD.",
  "ALBT": "ALLIEDBANKANDTRUSTCOMPANY(BAHA MAS) LIMITED",
  "AMRR": "BRITANNIA BANK AND TRUST LTD.",
  "ARNE": "ARNER BANK AND TRUST (BAHAMAS) LTD.",
  "ARUE": "BRITANNIASECURITIESLIMITEDMS.SAFIYA MAJOR",
  "BAHD": "BAHAMAS DEVELOPMENT BANK",
  "BASE": "BANCA DEL SEMPIONE (OVERSEAS) LTD",
  "BAVO": "BANCO VOTORANTIM S/A, NASSAU BRANCH",
  "BBHM": "BAC BAHAMAS BANK LTD.",
  "BBIN": "BANCO BOCOM BBM S.A.",
  "BBVI": "BANCO BILBAO VIZCAYA, NEW YORK BR.",
  "BIGA": "CREDIT SUISSE BRAZIL (BAHAMAS) LIMITED",
  "BKPR": "BANKPRO LIMITED",
  "BLIC": "HSBC PRIVATE BANK (SUISSE) SA",
  "BOFA": "BANKAMERICATRUSTBANKINGCORP (BAHAMAS) LTD",
  "BOTB": "BANK OF THE BAHAMAS LIMITED",
  "BPGE": "PASCHE BANK AND TRUST LIMITED",
  "BPOI": "BANCO POPULAR INTERNATIONAL LTD.",
  "BSAF": "BANK J. SAFRA SARASIN (BAHAMAS) LTD.",
  "BSCH": "BANCO SANTANDER BAHAMAS INTL LTD",
  "BSSA": "CBH (BAHAMAS) LTD.",
  "BTAM": "FIDELITY BANK (BAHAMAS) LIMITED",
  "CBBA": "ITAU UNIBANCO S.A. - NASSAU BRANCH",
  "CBBH": "CENTRAL BANK OF THE BAHAMAS,THE",
  "CBLU": "CORNER BANK (OVERSEAS) LIMITED",
  "CHAS": "CHASEMANHATTANTRUSTCORPORATION LIMITED",
  "CIBA": "CITITRUST (BAHAMAS) LTD.",
  "CIBC": "CIBC CARIBBEAN TRUST COMPANY (BAHAMAS) LIMITED",
  "CITI": "CITICORP BANKING CORPORATION",
  "COMW": "COMMONWEALTH BANK LIMITED",
  "CRES": "UBS AG, NASSAU BRANCH",
  "CUBL": "CAPITAL UNION BANK LTD",
  "DBTL": "DELTEC BANK AND TRUST LIMITED",
  "EFGB": "EFG BANK AND TRUST (BAHAMAS) LTD",
  "EIML": "EUROPEANINVESTMENTSMANAGEMENT LIMITED",
  "EQTT": "EQUITY BANK BAHAMAS LIMITED",
  "EUBO": "EUROBANCO BANK LIMITED",
  "FCIB": "CIBC CARIBBEAN BANK (BAHAMAS) LIMITED",
  "FICB": "FINANCE CORPORATION OF BAHAMAS LTD.",
  "FOBL": "FIRST OVERSEAS BANK LIMITED",
  "GBLI": "UBS AG, NASSAU BRANCH",
  "GLNG": "GILINGAM BANK AND TRUST LTD.",
  "GONE": "GONET BANK AND TRUST LIMITED",
  "GTBL": "GUARANTY TRUST BANK LIMITED",
  "HASE": "HANG SENG BANK (BAHAMAS) LTD.",
  "IIBB": "INTERNATIONAL INVESTMENT BANK LTD",
  "JSBB": "BANK J. SAFRA SARASIN (BAHAMAS) LTD",
  "KARL": "KARLA DERIVATIVES STRATEGIES FUND LTD.",
  "LOCY": "LOMBARD ODIER AND CIE (BAHAMAS) LIMITED",
  "MCRO": "MACRO BANK LIMITED",
  "MMGB": "MMG BANK AND TRUST LTD.",
  "NFZB": "UNION BANCAIRE PRIVEE, UBP SA",
  "NOSC": "SCOTIABANK (BAHAMAS) LTD.",
  "OBAT": "OCEANIC BANK AND TRUST LIMITED",
  "PICT": "PICTET BANK AND TRUST LIMITED",
  "PWOC": "PUBLICWORKERSCO-OPERATIVECREDIT UNION LIMITED",
  "RCTC": "ROYALBANKOFCANADATRUSTCOMPANY (BAHAMAS) LIMITED",
  "RFMB": "RF BANK AND TRUST (BAHAMAS) LIMITED",
  "ROYC": "RBCROYALBANK(BAHAMAS)LIMITED(FKA ROYAL BANK OF CANADA NASSAU)",
  "RUBA": "RURAL INTERNATIONAL BANK",
  "SCHT": "BANCOSANTANDERINTERNATIONALSA BAHAMAS BRANCH",
  "STGT": "STERLING BANK AND TRUST LIMITED",
  "SYCO": "SYZ BANK (BAHAMAS) LTD.",
  "TSWC": "TEACHERSANDSALARIEDWORKERSCO- OPERATIVE CREDIT UNION LIMITED",
  "USNA": "USTS NASSAU, BAHAMAS LTD.",
  "WNTR": "WINTERBOTHAMTRUSTCOMPANYLIMITED, THE"
}