{
  "ABMZ": "ABSA BANK MOCAMBIQUE, SA",
  "ABNG": "ACCESS BANK MOZAMBIQUE, SA",
  "BATS": "BRITISHAMERICANTOBACCOMOZAMBIQUE LIMITADA",
  "BDIG": "BANCO BIG MOCAMBIQUE, S.A.",
  "BIMO": "BANCO INTERNACIONAL DE MOCAMBIQUE, S.A.",
  "BMOC": "BANCO DE MOCAMBIQUE",
  "BNIM": "BANCO NACIONAL DE INVESTIMENTO, SA",
  "CGDI": "BANCO COMERCIAL E DE INVESTIMENTOS, SA.",
  "ECOC": "ECOBANK MOCAMBIQUE, S.A.",
  "FIRN": "FNB MOZAMBIQUE,SA BUILDING 33, FLOOR 4",
  "FRCG": "FIRST CAPITAL BANK SA",
  "ILBK": "BANCO PORTUGUES ATLANTICO",
  "MAIS": "BANCO MAIS, SA",
  "MERV": "NOSSO BANCO, SA",
  "MOZA": "MOZA BANCO SA",
  "SBIC": "STANDARD BANK SA",
  "SCBL": "STANDARDCHARTEREDBANKOF MOZAMBIQUE",
  "SOGE": "VISTA BANK MOCAMBIQUE SU, S.A.",
  "UNAF": "UBA MOCAMBIQUE,SA",
  "UNIC": "NEDBANK MOCAMBIQUE, S.A.",
  "VSTB": "VISTA BANK MOCAMBIQUE SU, S.A."
}