{"AIFN":"ALFIN BANCO S.A.","AMRK":"AMERIKA FINANCIERA S.A.","AZTK":"BANCO AZTECA DEL PERU, S.A.","BAIO":"BANCO IBEROAMERICANO","BANC":"BANCO DE LA NACION","BATS":"BRITISH AMERICAN TOBACCO DEL PERU HOLDINGS S.A.","BCON":"BANCO BBVA PERU","BCPL":"BANCO DE CREDITO DEL PERU","BDCM":"BANCO DE COMERCIO","BELP":"CETCO S.A.","BIFS":"BANCO INTERAMERICANO DE FINANZAS","BINP":"BANCO INTERNACIONAL DEL PERU (INTERBANK)","BKCH":"BANK OF CHINA (PERU) S.A.","BNPE":"BANCO BBVA PERU","BSAP":"BANCO SANTANDER PERU S.A.","BSUD":"SCOTIABANK PERU S.A.A.","CAFC":"CORPORACION ANDINA DE FOMENTO","CAPO":"CAMPOSOL","CBOL":"CREDICORP CAPITAL SOCIEDAD AGENTE DE BOLSA S.A.","CCST":"CELFIN CAPITAL S.A. SOCIEDAD AGENTE DE BOLSA","CHAS":"JP MORGAN BANCO DE INVERSION","CITI":"CITIBANK DEL PERU S.A.","COFD":"CORPORACION FINANCIERA DE DESARROLLO S.A. - COFIDE","CPDC":"COOPERATIVA DE AHORRO CREDITO EL PROGRESO DEL COMERCIANTE DE","CRED":"BANCO BCI PERU S.A.","CRHC":"CAJA RURAL DE AHORRO Y CREDITO CHAVIN SAA","CRPE":"BANCO CENTRAL DE RESERVA DEL PERU","CVLI":"CAVALI S.A I.C.L.V.","DEUT":"DEUTSCHE BANK (PERU) S.A.","EGPS":"ENEL GENERACION PERU S.A.A.","FCPE":"FINANCIERA DE CREDITO DEL PERU","FINA":"BANCO PICHINCHA","HBPE":"BANCO GNB PERU SA","ICBK":"ICBC PERU BANK","INTV":"INTERVALORES","KAES":"KALLPA SECURITIES S.A.B","MIBA":"MIBANCO, BANCO DE LA MICRO EMPRESA S.A.","PACC":"COOPERATIVA DE AHORRO CREDITO PACIFICO","SABM":"SABMILLER PERU","SCSG":"SEMINARIO Y CIA. SOCIEDAD AGENTE DE BOLSA S.A.","SECT":"SAMSUNG ELECTRONICS PERU S.A.C"}