{
  "ACAI": "ACESCO CARIBE, MFG.",
  "ACBI": "ANDCAPITAL BANK INTERNATIONAL CORP",
  "ADGI": "ADVANTAGE INTERNATIONAL BANK CORP.",
  "AFCP": "APPLIED FINANCE CAPITAL MANAGEMENT LLC",
  "AICI": "ALLIANCE CAPITAL INTERNATIONAL BANK INC",
  "AMTL": "AMERICAN INTERNATIONAL BANK LLC",
  "ARNR": "BANCARIBE INTERNATIONAL BANK, INC.",
  "ARVB": "ARIVAL BANK INTERNATIONAL CORP.",
  "BIPN": "EASYBANK INTERNATIONAL, INC.",
  "BPPR": "BANCO POPULAR DE PUERTO RICO",
  "CBLB": "CB INTERNATIONAL BANK LLC",
  "CFSU": "BANCOLOMBIA PUERTO RICO INTERNACION AL, INC.",
  "CIBP": "BNC INTERNATIONAL BANKING CORPORATION",
  "CITI": "CITIBANK N.A.",
  "DINT": "DIGITAL INTERNATIONAL BANK, INC.",
  "ESYI": "EPAYSYSTEMSINTERNATIONALLIMITED LIABILITY COMPANY",
  "FBPR": "FIRSTBANK PUERTO RICO",
  "FILC": "FACEBANK INTERNATIONAL CORPORATION",
  "FNTL": "FAIRWINDS INTERNATIONAL BANK, LLC",
  "GKBI": "TRIVEBANK INTERNATIONAL, CORP.",
  "IBII": "ITALBANK INTERNATIONAL, INC",
  "INTE": "INTERCAM BANCO INTERNACIONAL, INC.",
  "ITTL": "FV BANK INTERNATIONAL INC",
  "ITUL": "INTERNATIONAL UNION BANK LLC",
  "LATA": "TC LATIN AMERICA PARTNERS LLC",
  "MDIC": "MEDICI BANK INTERNATIONAL LLC",
  "MMGB": "MMG BANK INTERNATIONAL, INC.",
  "MULN": "ARETIBANK INTERNATIONAL INC.",
  "NDBK": "NODUS INTERNATIONAL BANK, INC.",
  "NINT": "NEXT BANK INTERNATIONAL, INC.",
  "NOSC": "ORIENTALBANK(FORMELYBBVAPUERTO RICO)",
  "OBPR": "ORIENTALBANK(FORMELYBBVAPUERTO RICO)",
  "PPUR": "POPULAR ASSET MANAGEMENT LLC",
  "SIEC": "STERN INTERNATIONAL BANK LLC",
  "STGN": "STRATEGIC BANK INTERNATIONAL CORP.",
  "TOLT": "TOLOMEO BANK INTERNATIONAL, CORP.",
  "WTCB": "WTC INTERNATIONAL BANK CORPORATION",
  "ZEIT": "ZENUS BANK INTERNATIONAL INC."
}